

        {
            "name": "single_train_dbg",
            "type": "python",
            "request": "launch",
            "program": "${workspaceFolder}/train.py",
            "env": {
                "WANDB_API_KEY": "19bd58fd59bd4e4acf77069250786a00cca6c680",
                "CUDA_VISIBLE_DEVICES": "1",
                "PYDEVD_WARN_SLOW_RESOLVE_TIMEOUT": "2",
            },
            "args": [
                "--name",
                "dkc9_v5_s400_mt",
                "--data_path",
                "/proj/vondrick3/basile/kubcon_v9/train/kubcon_v9_scn00400/",
                "--batch_size",
                "1",
                // "--num_workers",
                // "0",
                "--use_data_frac",
                "120",
                "--num_queries",
                "1",
                "--learn_rate",
                "1e-3",
                "--num_frames",
                "20",
                "--frame_height",
                "144",
                "--frame_width",
                "192",
                "--frame_rate",
                "12",
                "--frame_stride",
                "1",
                "--augs_2d",
                "1",
                "--augs_3d",
                "1",
                "--seeker_input_format",
                // "rgbd",
                "rgb",
                // "--seeker_query_format",
                // "uvt",
                // "--seeker_query_type",
                // "mask_token",
                // "--seeker_output_format",
                // "uvdo",
                // "--seeker_output_token",
                // "query",
                // "--seeker_output_type",
                // "gaussian",
                // "--seeker_frames",
                // "8",
                // "16",
                "--seeker_query_time",
                "0.2",
            ],
            "console": "integratedTerminal",
            "cwd": "${workspaceFolder}/"
        },
        {
            "name": "single_test_dbg",
            "type": "python",
            "request": "launch",
            "program": "${workspaceFolder}/eval/test.py",
            "env": {
                "WANDB_API_KEY": "19bd58fd59bd4e4acf77069250786a00cca6c680",
                "PYDEVD_WARN_SLOW_RESOLVE_TIMEOUT": "2",
            },
            "args": [
                "--resume",
                "dkbv2_s69_d1",
                "--name",
                "dkbv2_s69_d1_dt1",
                "--gpu_id",
                "1",
                "--data_path",
                "/mnt/dd2/kubbench_v2/kubbench_v2_scn069_box_push_container_slide/",
                "--num_workers",
                "0",
                "--use_data_frac",
                "10",
                "--num_queries",
                "8",
                "--store_results",
                "1",
                "--all_perturbs_views",
                "0",
            ],
            "console": "integratedTerminal",
            "cwd": "${workspaceFolder}/"
        },
